LICENSE.txt
README.md
setup.cfg
setup.py
buscarcep/__init__.py
buscarcep/cep.py
buscarcep.egg-info/PKG-INFO
buscarcep.egg-info/SOURCES.txt
buscarcep.egg-info/dependency_links.txt
buscarcep.egg-info/top_level.txt